{
  "data": {
    "id": "dis_3szfNAufCVwo6Sq26Ry0n2",
    "attributes": {
      "name": "Limited time discount code!",
      "code": "LTDEF2D8VU35",
      "amount": 20,
      "expires_at": "2026-06-11T21:54:41.754Z",
      "applies_to_products": [
        "prod_1sQIqWKENUzzXJtSoWZrUr",
        "prod_1vkQ4tab7bl4LcopLGVb64",
        "prod_2OCda6p9ogQBSDmbA2Y5ou",
        "prod_3RevXENXFXyrznI42m9cOP",
        "prod_4UUna65T2mEcZqxeygE6jo",
        "prod_5MydTlhSPfwzxNJRnf0qkJ",
        "prod_5WTF3NMjAyFXqUppgngpBP",
        "prod_6w7BbA5UVpkH2Y0RSf8cfg",
        "prod_YxsechXAgtRBnbJTezU4K",
        "prod_yfdPS88lK7kfwSjbv5qei"
      ]
    }
  }
}