{
  "jsonapi": {
    "version": "1.0"
  },
  "links": {
    "self": "https://api.lemonsqueezy.com/v1/discounts/849109"
  },
  "data": {
    "type": "discounts",
    "id": "849109",
    "attributes": {
      "store_id": 10640,
      "name": "Limited time discount code!",
      "code": "LTDZYF48DZ56",
      "amount": 20,
      "amount_type": "percent",
      "is_limited_to_products": false,
      "is_limited_redemptions": false,
      "max_redemptions": 0,
      "starts_at": null,
      "expires_at": "2025-10-11T10:20:37.000000Z",
      "duration": "once",
      "duration_in_months": 1,
      "status": "published",
      "status_formatted": "Published",
      "created_at": "2025-10-11T06:20:37.000000Z",
      "updated_at": "2025-10-11T06:20:37.000000Z",
      "test_mode": false
    },
    "relationships": {
      "store": {
        "links": {
          "related": "https://api.lemonsqueezy.com/v1/discounts/849109/store",
          "self": "https://api.lemonsqueezy.com/v1/discounts/849109/relationships/store"
        }
      },
      "variants": {
        "links": {
          "related": "https://api.lemonsqueezy.com/v1/discounts/849109/variants",
          "self": "https://api.lemonsqueezy.com/v1/discounts/849109/relationships/variants"
        }
      },
      "discount-redemptions": {
        "links": {
          "related": "https://api.lemonsqueezy.com/v1/discounts/849109/discount-redemptions",
          "self": "https://api.lemonsqueezy.com/v1/discounts/849109/relationships/discount-redemptions"
        }
      }
    },
    "links": {
      "self": "https://api.lemonsqueezy.com/v1/discounts/849109"
    }
  }
}